<?xml version="1.0" encoding="UTF-8"?>
<?xml-stylesheet type="text/xsl" href="ftml_wf.xsl"?>
<ftml version="1.0">
  <head>
    <columns class="2%" comment="2%" label="10%" string="5%"/>
    <description>Test of Awami - Letter Coverage</description>
    <fontscale>100</fontscale>
    <fontsrc>local('Awami Nastaliq Alpha Test'), url(Awami_alpha1.ttf)</fontsrc>
    <title>Test of Awami - Random Words</title>
    <styles><style feats=' ' name="default"/></styles>
  </head>
  <testgroup label="Group 1">
    <test label="word 1" rtl="True"><string>&#x0622;&#x062A;&#x0650;&#x0634;&#x0650;&#x06CC;&#x0646;</string><comment></comment></test>
    <test label="word 2" rtl="True"><string>&#x0622;&#x0631;&#x0627;&#x0645;&#x06AF;&#x0627;&#x06C1;&#x0648;&#x06BA;</string></test>
    <test label="word 3" rtl="True"><string>&#x0633;&#x0628;&#x0651;&#x06A9;&#x06CC;</string></test>
    <test label="word 4" rtl="True"><string>&#x0633;&#x06D2;&#x0635;&#x064F;&#x062D;&#x0628;&#x062A;</string></test>
    <test label="word 5" rtl="True"><string>&#x0634;&#x062E;&#x0635;&#x0650;&#x06CC;&#x0645;&#x0627;&#x06C1;</string></test>
    <test label="word 6" rtl="True"><string>&#x0637;&#x06CC;&#x062A;&#x06BE;</string></test>
    <test label="word 7" rtl="True"><string>&#x0639;&#x0648;&#x0641;&#x0644;</string></test>
    <test label="word 8" rtl="True"><string>&#x0639;&#x064E;&#x0645;&#x0627;&#x0644;&#x06CC;&#x0642;</string></test>
    <test label="word 9" rtl="True"><string>&#x0639;&#x0650;&#x0645;&#x0651;&#x06CC;&#x06C1;&#x064F;&#x0648;&#x062F;</string></test>
    <test label="word 10" rtl="True"><string>&#x0648;&#x0627;&#x0633;&#x0637;&#x06C1;</string></test>
    <test label="word 11" rtl="True"><string>&#x067E;&#x064E;&#x06BE;&#x06CC;&#x0644;&#x0627;&#x0626;&#x06CC;</string></test>
    <test label="word 12" rtl="True"><string>&#x067E;&#x064E;&#x06CC;&#x062F;&#x0627;&#x06A9;&#x0631;</string></test>
    <test label="word 13" rtl="True"><string>&#x06CC;&#x06C1;&#x064F;&#x0648;&#x0633;&#x0641;&#x0637;</string></test>
    <test label="word 14" rtl="True"><string>&#x0627;&#x0686;&#x06BE;&#x0627;&#x0651;&#x0644;&#x06AF;&#x062A;&#x0627;</string></test>
    <test label="word 15" rtl="True"><string>&#x0628;&#x063A;&#x064E;&#x06CC;&#x0631;&#x06A9;&#x0644;&#x0627;&#x0645;</string></test>
    <test label="word 16" rtl="True"><string>&#x0633;&#x0645;&#x062F;&#x06BE;&#x06CC;&#x0627;&#x0646;&#x06C1;</string></test>
  </testgroup>
</ftml>
